yakh/__init__.py
yakh/_yakh.py
yakh/key/__init__.py
yakh/key/_key.py
python_yakh-0.4.1.dist-info/LICENSE
python_yakh-0.4.1.dist-info/METADATA
python_yakh-0.4.1.dist-info/WHEEL
python_yakh-0.4.1.dist-info/RECORD
