Metadata-Version: 2.3
Name: python-yakh
Version: 0.4.1
Summary: Yet Another Keypress Handler
License: MIT
Keywords: python,keypress,key,keyboard
Author: petereon
Author-email: pvyboch1@gmail.com
Requires-Python: >=3.7.8,<4.0.0
Classifier: License :: OSI Approved :: MIT License
Classifier: Programming Language :: Python :: 3
Classifier: Programming Language :: Python :: 3.8
Classifier: Programming Language :: Python :: 3.9
Classifier: Programming Language :: Python :: 3.10
Classifier: Programming Language :: Python :: 3.11
Classifier: Programming Language :: Python :: 3.12
Classifier: Programming Language :: Python :: 3.13
Project-URL: Repository, https://github.com/petereon/yakh
